Metadata-Version: 1.1
Name: bdgenomics.workflows
Version: 0.1.0
Summary: A repository of genomic workflows developed by the UC Berkeley AMPLab and UCSC Computational Genomics lab that use Toil to run ADAM/BDG tools
Home-page: https://github.com/bigdatagenomics/workflows
Author: UC Berkeley AMP Lab
Author-email: adam-developers@googlegroups.com
License: UNKNOWN
Platform: UNKNOWN
Classifier: License :: OSI Approved :: Apache Software License
